Workbook

Sheet Dettaglio costi
A1: CSN5 Grant Giovani 2026 — Dettaglio dei costi
A2: Compilare le celle gialle. Gli importi sono IVA inclusa; indicare eventuali eccezioni nelle note. Limite: 75.000 € per anno.
A4: ID | B4: Anno | C4: Categoria | D4: Componente / attività | E4: Specifiche o calcolo | F4: WP | G4: Costo unitario (€) | H4: Quantità | I4: Costo richiesto (€) | J4: In-kind (€) | K4: Fornitore / fonte | L4: Preventivo | M4: Note / giustificazione
A5: C01 | B5: 1 | C5: Attrezzature | D5: Cristallo/i analizzatore/i | E5: Materiale, geometria, dimensioni e intervallo energetico da definire dopo WP1 | F5: WP2 | I5: =IF(OR(G5="",H5=""),"",G5*H5) | J5: 0 | L5: Q01 | M5: Ottica selezionata in base al compromesso efficienza–risoluzione
A6: C02 | B6: 1 | C6: Attrezzature | D6: Stadi motorizzati e controller | E6: Numero assi, corsa, carico e ripetibilità | F6: WP2 | I6: =IF(OR(G6="",H6=""),"",G6*H6) | J6: 0 | L6: Q02 | M6: Scansione energetica e allineamento riproducibile
A7: C03 | B7: 1 | C7: Attrezzature | D7: Rivelatore SDD ed elettronica | E7: Area, risoluzione, rate capability e pile-up da giustificare quantitativamente | F7: WP2 | H7: 1 | I7: =IF(OR(G7="",H7=""),"",G7*H7) | J7: 0 | L7: Q03 | M7: Confrontare esplicitamente con gli SDD già disponibili
A8: C04 | B8: 1 | C8: Attrezzature | D8: Meccanica e supporti di precisione | E8: Supporti cristallo, campione e rivelatore; componenti da vuoto se necessari | F8: WP2 | I8: =IF(OR(G8="",H8=""),"",G8*H8) | J8: 0 | L8: Q04 | M8: Integrazione del prototipo
A9: C05 | B9: 1 | C9: Calcolo | D9: Workstation di simulazione e analisi | E9: Configurazione CPU/GPU/RAM motivata dai carichi SHADOW4/Geant4 | F9: WP1 | H9: 1 | I9: =IF(OR(G9="",H9=""),"",G9*H9) | J9: 0 | L9: Q05 | M9: Eliminare se sono disponibili risorse adeguate
A10: C06 | B10: 1 | C10: Consumi | D10: Campioni e materiali di calibrazione | E10: Target, standard, finestre, supporti e gas | F10: WP3 | H10: 1 | I10: =IF(OR(G10="",H10=""),"",G10*H10) | J10: 0 | M10: Specificare benchmark ed edge >20 keV
A11: C07 | B11: 1 | C11: Servizi | D11: Lavorazioni meccaniche specialistiche | E11: Lavorazioni non realizzabili internamente | F11: WP2 | H11: 1 | I11: =IF(OR(G11="",H11=""),"",G11*H11) | J11: 0 | L11: Q06 | M11: Distinguere dai contributi dei servizi LNF
A12: C08 | B12: 1 | C12: Missioni | D12: Campagna sperimentale 1 | E12: Sede; n. persone × n. giorni × costo/giorno + viaggio | F12: WP3 | H12: 1 | I12: =IF(OR(G12="",H12=""),"",G12*H12) | J12: 0 | M12: Dettagliare destinazione e scopo
A13: C09 | B13: 2 | C13: Attrezzature | D13: Cella operando / ambiente campione | E13: Geometria, controllo e compatibilità con fluorescenza XAS | F13: WP4 | H13: 1 | I13: =IF(OR(G13="",H13=""),"",G13*H13) | J13: 0 | L13: Q07 | M13: Acquistare solo dopo la validazione della configurazione
A14: C10 | B14: 2 | C14: Consumi | D14: Campioni e materiali per misure operando | E14: Materiali attivi, celle, finestre, elettroliti o gas | F14: WP4 | H14: 1 | I14: =IF(OR(G14="",H14=""),"",G14*H14) | J14: 0 | M14: Collegare agli osservabili XAS previsti
A15: C11 | B15: 2 | C15: Servizi | D15: Lavorazioni e integrazione finale | E15: Adeguamenti dopo la validazione del prototipo | F15: WP2/WP4 | H15: 1 | I15: =IF(OR(G15="",H15=""),"",G15*H15) | J15: 0 | L15: Q08
A16: C12 | B16: 2 | C16: Missioni | D16: Campagne di validazione / operando | E16: Sede; n. campagne × persone × giorni, viaggio incluso | F16: WP3/WP4 | H16: 1 | I16: =IF(OR(G16="",H16=""),"",G16*H16) | J16: 0 | M16: Separare le campagne se hanno sedi o finalità diverse
A17: C13 | B17: 2 | C17: Missioni | D17: Conferenza con presentazione orale | E17: Indicare la conferenza o il criterio di selezione | F17: Disseminazione | H17: 1 | I17: =IF(OR(G17="",H17=""),"",G17*H17) | J17: 0 | M17: Ammissibile se associata a presentazione orale
A18: IK01 | B18: 1 | C18: In-kind | D18: Setup VOXES disponibile a LNF | E18: Tubo X, ottica, schermature, movimentazione e DAQ effettivamente disponibili | F18: WP2/WP3 | G18: 0 | H18: 1 | I18: 0 | K18: INFN-LNF | L18: Inventario | M18: Valorizzare solo componenti realmente utilizzabili
A19: IK02 | B19: 1 | C19: In-kind | D19: Rivelatori già disponibili | E19: Modello, area attiva, risoluzione e stato operativo | F19: WP2/WP3 | G19: 0 | H19: 1 | I19: 0 | K19: INFN-LNF | L19: Inventario
A20: IK03 | B20: 2 | C20: In-kind | D20: Supporto tecnico e infrastrutture | E20: Officina, laboratorio, sicurezza e servizi tecnici | F20: WP2/WP4 | G20: 0 | H20: 1 | I20: 0 | K20: INFN-LNF | L20: Dichiarazione | M20: Evitare valorizzazioni non documentabili

Sheet Riepilogo
A1: Riepilogo finanziario
A2: Il limite annuo è 75.000 €. Le formule leggono il foglio Dettaglio costi.
A4: Categoria | B4: Anno 1 | C4: Anno 2 | D4: Totale richiesto (€) | E4: Totale in-kind (€)
A5: Attrezzature | B5: =SUMIFS('Dettaglio costi'!$I$5:$I$200,'Dettaglio costi'!$C$5:$C$200,$A5,'Dettaglio costi'!$B$5:$B$200,B$4) | C5: =SUMIFS('Dettaglio costi'!$I$5:$I$200,'Dettaglio costi'!$C$5:$C$200,$A5,'Dettaglio costi'!$B$5:$B$200,C$4) | D5: =SUM(B5:C5) | E5: =SUMIFS('Dettaglio costi'!$J$5:$J$200,'Dettaglio costi'!$C$5:$C$200,$A5)
A6: Calcolo | B6: =SUMIFS('Dettaglio costi'!$I$5:$I$200,'Dettaglio costi'!$C$5:$C$200,$A6,'Dettaglio costi'!$B$5:$B$200,B$4) | C6: =SUMIFS('Dettaglio costi'!$I$5:$I$200,'Dettaglio costi'!$C$5:$C$200,$A6,'Dettaglio costi'!$B$5:$B$200,C$4) | D6: =SUM(B6:C6) | E6: =SUMIFS('Dettaglio costi'!$J$5:$J$200,'Dettaglio costi'!$C$5:$C$200,$A6)
A7: Consumi | B7: =SUMIFS('Dettaglio costi'!$I$5:$I$200,'Dettaglio costi'!$C$5:$C$200,$A7,'Dettaglio costi'!$B$5:$B$200,B$4) | C7: =SUMIFS('Dettaglio costi'!$I$5:$I$200,'Dettaglio costi'!$C$5:$C$200,$A7,'Dettaglio costi'!$B$5:$B$200,C$4) | D7: =SUM(B7:C7) | E7: =SUMIFS('Dettaglio costi'!$J$5:$J$200,'Dettaglio costi'!$C$5:$C$200,$A7)
A8: Servizi | B8: =SUMIFS('Dettaglio costi'!$I$5:$I$200,'Dettaglio costi'!$C$5:$C$200,$A8,'Dettaglio costi'!$B$5:$B$200,B$4) | C8: =SUMIFS('Dettaglio costi'!$I$5:$I$200,'Dettaglio costi'!$C$5:$C$200,$A8,'Dettaglio costi'!$B$5:$B$200,C$4) | D8: =SUM(B8:C8) | E8: =SUMIFS('Dettaglio costi'!$J$5:$J$200,'Dettaglio costi'!$C$5:$C$200,$A8)
A9: Missioni | B9: =SUMIFS('Dettaglio costi'!$I$5:$I$200,'Dettaglio costi'!$C$5:$C$200,$A9,'Dettaglio costi'!$B$5:$B$200,B$4) | C9: =SUMIFS('Dettaglio costi'!$I$5:$I$200,'Dettaglio costi'!$C$5:$C$200,$A9,'Dettaglio costi'!$B$5:$B$200,C$4) | D9: =SUM(B9:C9) | E9: =SUMIFS('Dettaglio costi'!$J$5:$J$200,'Dettaglio costi'!$C$5:$C$200,$A9)
A10: Altri costi | B10: =SUMIFS('Dettaglio costi'!$I$5:$I$200,'Dettaglio costi'!$C$5:$C$200,$A10,'Dettaglio costi'!$B$5:$B$200,B$4) | C10: =SUMIFS('Dettaglio costi'!$I$5:$I$200,'Dettaglio costi'!$C$5:$C$200,$A10,'Dettaglio costi'!$B$5:$B$200,C$4) | D10: =SUM(B10:C10) | E10: =SUMIFS('Dettaglio costi'!$J$5:$J$200,'Dettaglio costi'!$C$5:$C$200,$A10)
A11: TOTALE | B11: =SUM(B5:B10) | C11: =SUM(C5:C10) | D11: =SUM(D5:D10) | E11: =SUM(E5:E10)
A13: Margine rispetto al limite annuo | B13: =75000-B11 | C13: =75000-C11
A14: Verifica limite | B14: =IF(B11<=75000,"OK","SUPERATO") | C14: =IF(C11<=75000,"OK","SUPERATO")

Sheet Preventivi
A1: Registro preventivi
A3: Codice | B3: Voce collegata | C3: Fornitore | D3: Data | E3: Importo IVA incl. (€) | F3: Validità | G3: File / riferimento | H3: Stato e note
A4: Q01
A5: Q02
A6: Q03
A7: Q04
A8: Q05
A9: Q06
A10: Q07
A11: Q08
A14: Nota | B14: Il template richiede un preventivo per le attrezzature e un preventivo dettagliato per ogni voce superiore a 2.000 €.

Sheet Istruzioni
A1: Istruzioni per il budget
A3: Vincolo | B3: Massimo 75.000 € per ciascun anno; durata del progetto: 24 mesi.
A4: Dettaglio | B4: Riportare la richiesta per ogni anno e descrivere ogni voce in modo verificabile.
A5: Preventivi | B5: Allegare un preventivo per le attrezzature e per ogni singola voce superiore a 2.000 €.
A6: Missioni | B6: Separare attività sperimentali, riunioni e conferenze. Per le conferenze indicare quella prevista e la presentazione orale.
A7: In-kind | B7: Tenere distinti i costi richiesti dalle risorse già disponibili; valorizzare soltanto contributi documentabili.
A8: Coerenza | B8: Collegare ogni costo a WP, task, deliverable o requisito tecnico; evitare voci generiche.
A9: Esclusioni | B9: Il progetto non può finanziare borse, contratti di ricerca o incarichi a terzi.
A10: Celle gialle | B10: Sono campi da compilare o verificare. Le celle con formule non devono essere sovrascritte.
